pymatflow/__init__.py
pymatflow/abinit/__init__.py
pymatflow/abinit/abinit.py
pymatflow/abinit/bse.py
pymatflow/abinit/dfpt.py
pymatflow/abinit/group.py
pymatflow/abinit/md.py
pymatflow/abinit/namelist.py
pymatflow/abinit/neb.py
pymatflow/abinit/opt.py
pymatflow/abinit/optic.py
pymatflow/abinit/optic_namelist.py
pymatflow/abinit/phonopy.py
pymatflow/abinit/static.py
pymatflow/abinit/submit.py
pymatflow/abinit/base/__init__.py
pymatflow/abinit/base/dfpt.py
pymatflow/abinit/base/electrons.py
pymatflow/abinit/base/files.py
pymatflow/abinit/base/guard.py
pymatflow/abinit/base/input.py
pymatflow/abinit/base/ions.py
pymatflow/abinit/base/misc.py
pymatflow/abinit/base/properties.py
pymatflow/abinit/base/system.py
pymatflow/abinit/base/xyz.py
pymatflow/abinit/post/__init__.py
pymatflow/abinit/post/bands.py
pymatflow/abinit/post/dfpt.py
pymatflow/abinit/post/md.py
pymatflow/abinit/post/neb.py
pymatflow/abinit/post/opt.py
pymatflow/abinit/post/scf.py
pymatflow/base/__init__.py
pymatflow/base/atom.py
pymatflow/base/element.py
pymatflow/base/xyz.py
pymatflow/builder/__init__.py
pymatflow/builder/cluster.py
pymatflow/builder/slab.py
pymatflow/builder/tool.py
pymatflow/charge/__init__.py
pymatflow/charge/chg_vasp.py
pymatflow/cmd/__init__.py
pymatflow/cmd/cp2k_parser.py
pymatflow/cmd/lmpflow.py
pymatflow/cmd/matflow.py
pymatflow/cmd/matflow_abinit.py
pymatflow/cmd/matflow_cp2k.py
pymatflow/cmd/matflow_dftbplus.py
pymatflow/cmd/matflow_qe.py
pymatflow/cmd/matflow_siesta.py
pymatflow/cmd/matflow_vasp.py
pymatflow/cmd/postflow.py
pymatflow/cmd/qe_parser.py
pymatflow/cmd/structflow.py
pymatflow/cp2k/__init__.py
pymatflow/cp2k/cp2k.py
pymatflow/cp2k/cp2k_dev.py
pymatflow/cp2k/gen_force_eval.py
pymatflow/cp2k/gen_global.py
pymatflow/cp2k/lr.py
pymatflow/cp2k/lr_dev.py
pymatflow/cp2k/md.py
pymatflow/cp2k/md_dev.py
pymatflow/cp2k/mp2.py
pymatflow/cp2k/mp2_dev.py
pymatflow/cp2k/neb.py
pymatflow/cp2k/neb_dev.py
pymatflow/cp2k/opt.py
pymatflow/cp2k/opt_dev.py
pymatflow/cp2k/phonopy.py
pymatflow-0.1.1a4.dist-info/LICENSE
pymatflow-0.1.1a4.dist-info/METADATA
pymatflow-0.1.1a4.dist-info/WHEEL
pymatflow-0.1.1a4.dist-info/entry_points.txt
pymatflow-0.1.1a4.dist-info/top_level.txt
pymatflow-0.1.1a4.dist-info/RECORD
